{
  "title": "🌍 MYCELIUM — REAL WORLD MULTI-AGENT DEMONSTRATION REPORT",
  "generated_at": "2026-04-03 08:10:13 UTC",
  "chains": [
    {
      "name": "Crypto Price Translation",
      "description": "Get Bitcoin price → Convert to INR → Translate to Hindi",
      "steps": [
        {
          "step": 1,
          "label": "Get Bitcoin Price in USD",
          "agent": "crypto",
          "status": "agent_not_found"
        }
      ],
      "total_time_ms": 2253.9,
      "status": "failed",
      "started_at": "2026-04-03T08:10:16.306253+00:00",
      "completed_at": "2026-04-03T08:10:18.560220+00:00"
    },
    {
      "name": "Global Weather in Hindi",
      "description": "Get REAL weather of Tokyo → Translate to Hindi",
      "steps": [
        {
          "step": 1,
          "label": "Get Live Weather for Tokyo",
          "agent": "weather",
          "status": "agent_not_found"
        }
      ],
      "total_time_ms": 2269.3,
      "status": "failed",
      "started_at": "2026-04-03T08:10:18.560799+00:00",
      "completed_at": "2026-04-03T08:10:20.830084+00:00"
    },
    {
      "name": "Knowledge Translation",
      "description": "Get Wikipedia summary of 'Artificial Intelligence' → Translate to Hindi",
      "steps": [
        {
          "step": 1,
          "label": "Get AI Wikipedia Summary",
          "agent": "wiki",
          "status": "agent_not_found"
        }
      ],
      "total_time_ms": 2220.5,
      "status": "failed",
      "started_at": "2026-04-03T08:10:20.830999+00:00",
      "completed_at": "2026-04-03T08:10:23.051509+00:00"
    },
    {
      "name": "Multi-City Weather",
      "description": "Get REAL weather for Mumbai and convert temperature description to Japanese",
      "steps": [
        {
          "step": 1,
          "label": "Mumbai Weather",
          "agent": "weather",
          "status": "agent_not_found"
        }
      ],
      "total_time_ms": 2236.6,
      "status": "failed",
      "started_at": "2026-04-03T08:10:23.051788+00:00",
      "completed_at": "2026-04-03T08:10:25.288446+00:00"
    },
    {
      "name": "Ethereum Full Pipeline",
      "description": "Ethereum price → Convert to EUR → Get Ethereum Wikipedia info",
      "steps": [
        {
          "step": 1,
          "label": "Get Ethereum Price",
          "agent": "crypto",
          "status": "agent_not_found"
        }
      ],
      "total_time_ms": 2236.8,
      "status": "failed",
      "started_at": "2026-04-03T08:10:25.289130+00:00",
      "completed_at": "2026-04-03T08:10:27.525975+00:00"
    }
  ],
  "summary": {
    "total_chains": 5,
    "successful_chains": 0,
    "total_steps_executed": 5,
    "steps_with_real_data": 0,
    "unique_agents_used": 0,
    "total_time_ms": 11217.1
  }
}